<?xml version="1.0" encoding="UTF-8"?>
<!DOCTYPE mapper PUBLIC "-//mybatis.org//DTD Mapper 3.0//EN" "http://mybatis.org/dtd/mybatis-3-mapper.dtd">
<mapper namespace="cn.ponyzhang.server.mapper.RedDetailMapper">
  <resultMap id="BaseResultMap" type="cn.ponyzhang.server.entity.RedDetail">
    <!--
      WARNING - @mbg.generated
      This element is automatically generated by MyBatis Generator, do not modify.
      This element was generated on Wed Nov 03 10:15:08 CST 2021.
    -->
    <id column="id" jdbcType="INTEGER" property="id" />
    <result column="record_id" jdbcType="INTEGER" property="recordId" />
    <result column="amount" jdbcType="DECIMAL" property="amount" />
    <result column="is_active" jdbcType="TINYINT" property="isActive" />
    <result column="create_time" jdbcType="TIMESTAMP" property="createTime" />
  </resultMap>
  <delete id="deleteByPrimaryKey" parameterType="java.lang.Integer">
    <!--
      WARNING - @mbg.generated
      This element is automatically generated by MyBatis Generator, do not modify.
      This element was generated on Wed Nov 03 10:15:08 CST 2021.
    -->
    delete from red_detail
    where id = #{id,jdbcType=INTEGER}
  </delete>
  <insert id="insert" parameterType="cn.ponyzhang.server.entity.RedDetail">
    <!--
      WARNING - @mbg.generated
      This element is automatically generated by MyBatis Generator, do not modify.
      This element was generated on Wed Nov 03 10:15:08 CST 2021.
    -->
    insert into red_detail (id, record_id, amount, 
      is_active, create_time)
    values (#{id,jdbcType=INTEGER}, #{recordId,jdbcType=INTEGER}, #{amount,jdbcType=DECIMAL}, 
      #{isActive,jdbcType=TINYINT}, #{createTime,jdbcType=TIMESTAMP})
  </insert>
  <update id="updateByPrimaryKey" parameterType="cn.ponyzhang.server.entity.RedDetail">
    <!--
      WARNING - @mbg.generated
      This element is automatically generated by MyBatis Generator, do not modify.
      This element was generated on Wed Nov 03 10:15:08 CST 2021.
    -->
    update red_detail
    set record_id = #{recordId,jdbcType=INTEGER},
      amount = #{amount,jdbcType=DECIMAL},
      is_active = #{isActive,jdbcType=TINYINT},
      create_time = #{createTime,jdbcType=TIMESTAMP}
    where id = #{id,jdbcType=INTEGER}
  </update>
  <select id="selectByPrimaryKey" parameterType="java.lang.Integer" resultMap="BaseResultMap">
    <!--
      WARNING - @mbg.generated
      This element is automatically generated by MyBatis Generator, do not modify.
      This element was generated on Wed Nov 03 10:15:08 CST 2021.
    -->
    select id, record_id, amount, is_active, create_time
    from red_detail
    where id = #{id,jdbcType=INTEGER}
  </select>
  <select id="selectAll" resultMap="BaseResultMap">
    <!--
      WARNING - @mbg.generated
      This element is automatically generated by MyBatis Generator, do not modify.
      This element was generated on Wed Nov 03 10:15:08 CST 2021.
    -->
    select id, record_id, amount, is_active, create_time
    from red_detail
  </select>
</mapper>